snakemake_logger_plugin_flowo/__init__.py
snakemake_logger_plugin_flowo/__main__.py
snakemake_logger_plugin_flowo/config.py
snakemake_logger_plugin_flowo/event_handlers.py
snakemake_logger_plugin_flowo/log_handler.py
snakemake_logger_plugin_flowo/parsers.py
snakemake_logger_plugin_flowo/session.py
snakemake_logger_plugin_flowo/models/__init__.py
snakemake_logger_plugin_flowo/models/base.py
snakemake_logger_plugin_flowo/models/enums.py
snakemake_logger_plugin_flowo/models/error.py
snakemake_logger_plugin_flowo/models/file.py
snakemake_logger_plugin_flowo/models/job.py
snakemake_logger_plugin_flowo/models/rule.py
snakemake_logger_plugin_flowo/models/workflow.py
snakemake_logger_plugin_flowo-0.1.8.dist-info/METADATA
snakemake_logger_plugin_flowo-0.1.8.dist-info/WHEEL
snakemake_logger_plugin_flowo-0.1.8.dist-info/entry_points.txt
snakemake_logger_plugin_flowo-0.1.8.dist-info/licenses/LICENSE
snakemake_logger_plugin_flowo-0.1.8.dist-info/RECORD
