Metadata-Version: 2.4
Name: snakemake-logger-plugin-flowo
Version: 0.1.8
Summary: A Snakemake logger plugin that stores workflow execution data in PostgreSQL
Project-URL: Homepage, https://github.com/jmzhang1911/snakemake-logger-plugin-flowo
Project-URL: Repository, https://github.com/jmzhang1911/snakemake-logger-plugin-flowo
Project-URL: Issues, https://github.com/jmzhang1911/snakemake-logger-plugin-flowo/issues
Author-email: Haomiao Zhang <zhanghm@iregene.com>, Jingmin Zhang <zhangjm@iregene.com>
License-File: LICENSE
Keywords: logger,plugin,postgresql,snakemake,workflow
Classifier: Development Status :: 3 - Alpha
Classifier: Intended Audience :: Developers
Classifier: License :: OSI Approved :: MIT License
Classifier: Programming Language :: Python :: 3
Classifier: Programming Language :: Python :: 3.12
Classifier: Topic :: Scientific/Engineering :: Bio-Informatics
Classifier: Topic :: Software Development :: Libraries :: Python Modules
Requires-Python: >=3.12
Requires-Dist: psycopg2-binary>=2.9.9
Requires-Dist: pydantic-settings>=2.9.1
Requires-Dist: pydantic>=2.11.5
Requires-Dist: pygments>=2.19.2
Requires-Dist: snakemake-interface-logger-plugins>=1.2.3
Requires-Dist: snakemake>=9.6.2
Requires-Dist: sqlalchemy>=2.0.41
